morph_impl/__init__.py
morph_impl/classes.py
morph_impl/contentPack_processing.py
morph_impl/createConfigs.py
morph_impl/cypher.py
morph_impl/file_ImportScript.py
morph_impl/file_handler.py
morph_impl/getBearerToken.py
morph_impl/group.py
morph_impl/init_contentPack.py
morph_impl/initapp.py
morph_impl/input.py
morph_impl/license.py
morph_impl/morph_log.py
morph_impl/role.py
morph_impl/tasks.py
morph_impl/user_selection.py
morph_impl/users.py
morph_impl/whitelabel.py
morph_impl/wiki.py
morph_impl/workflows.py
morph_impl/yaml_validator.py
morph_impl/schema/__init__.py
morph_impl/schema/aws_Clouds.py
morph_impl/schema/azure_Clouds.py
morph_impl/schema/cypher.py
morph_impl/schema/groups.py
morph_impl/schema/inputs.py
morph_impl/schema/roles.py
morph_impl/schema/templates.py
morph_impl/schema/whitelabel.py
morph_impl-0.0.8.18.dist-info/LICENSE
morph_impl-0.0.8.18.dist-info/METADATA
morph_impl-0.0.8.18.dist-info/WHEEL
morph_impl-0.0.8.18.dist-info/top_level.txt
morph_impl-0.0.8.18.dist-info/RECORD
