Metadata-Version: 2.1
Name: morph-impl
Version: 0.0.8.18
Summary: morph_impl is a python package to help implement MorpheusData platform. 
Home-page: https://gitlab.com/jaredlutgen/morpheus-implementation.git
Author: Jared Lutgen
Author-email: jlutgen@morpheusdata.com
License: MIT
Platform: UNKNOWN
Classifier: Development Status :: 2 - Pre-Alpha
Classifier: License :: OSI Approved :: MIT License
Classifier: Programming Language :: Python
Classifier: Programming Language :: Python :: 3.8
Classifier: Topic :: Software Development :: Libraries
Classifier: Topic :: Software Development :: Libraries :: Python Modules
Classifier: Intended Audience :: Developers
Classifier: Intended Audience :: Information Technology
Classifier: Intended Audience :: System Administrators
Requires-Python: >=3.8
Requires-Dist: PyYAML
Requires-Dist: cerberus
Requires-Dist: pillow
Requires-Dist: requests
Requires-Dist: tqdm
